{
    "idPorten": {
        "issuer": "https://oidc-yt2.difi.eon.no/idporten-oidc-provider",
        "authorizationEndpoint": "https://oidc-ver2.difi.no/idporten-oidc-provider/authorize"
    },
    "tenants": {
        "317e06b8-040b-43ad-9ced-565b3ae3f6d0": {
            "domain": "",
            "tenantIdClaims": [
                "3352d47d-c154-4457-b3fb-8a2efb725113"
            ]
        },
        "58846808-ff48-4022-8f05-658dc24adace": {
            "domain": "",
            "tenantIdClaims": [
                "1c51e03c-680e-4c38-92a0-0f1b96c57d3f"
            ]
        }
    },
    "identityDetailsUrl": "http://host.docker.internal:5100/.aksio/me"
}
